ansiblecmdb/__init__.py
ansiblecmdb/ansible_cmdb.py
ansiblecmdb/ansible_via_api.py
ansiblecmdb/ihateyaml.py
ansiblecmdb/parser.py
ansiblecmdb/render.py
ansiblecmdb/util.py
ansiblecmdb/data/static/images/sort_asc.png
ansiblecmdb/data/static/images/sort_both.png
ansiblecmdb/data/static/images/sort_desc.png
ansiblecmdb/data/static/js/jquery-1.10.2.min.js
ansiblecmdb/data/static/js/jquery.dataTables.css
ansiblecmdb/data/static/js/jquery.dataTables.js
ansiblecmdb/data/tpl/csv.tpl
ansiblecmdb/data/tpl/html_fancy.tpl
ansiblecmdb/data/tpl/html_fancy_defs.html
ansiblecmdb/data/tpl/html_fancy_split.py
ansiblecmdb/data/tpl/html_fancy_split_detail.tpl
ansiblecmdb/data/tpl/html_fancy_split_overview.tpl
ansiblecmdb/data/tpl/json.tpl
ansiblecmdb/data/tpl/markdown.tpl
ansiblecmdb/data/tpl/markdown_split.py
ansiblecmdb/data/tpl/markdown_split_detail.tpl
ansiblecmdb/data/tpl/markdown_split_overview.tpl
ansiblecmdb/data/tpl/sql.tpl
ansiblecmdb/data/tpl/txt_table.tpl
rami_ansible_cmdb-1.33.0.data/scripts/ansible-cmdb
rami_ansible_cmdb-1.33.0.data/scripts/ansible-cmdb.py
rami_ansible_cmdb-1.33.0.dist-info/LICENSE
rami_ansible_cmdb-1.33.0.dist-info/METADATA
rami_ansible_cmdb-1.33.0.dist-info/WHEEL
rami_ansible_cmdb-1.33.0.dist-info/top_level.txt
rami_ansible_cmdb-1.33.0.dist-info/RECORD
